qdesignoptimizer/__init__.py
qdesignoptimizer/design_analysis.py
qdesignoptimizer/design_analysis_types.py
qdesignoptimizer/estimation/__init__.py
qdesignoptimizer/estimation/classical_model_decay_into_charge_line.py
qdesignoptimizer/logger.py
qdesignoptimizer/sim_capacitance_matrix.py
qdesignoptimizer/sim_plot_progress.py
qdesignoptimizer/utils/__init__.py
qdesignoptimizer/utils/chip_generation.py
qdesignoptimizer/utils/names_design_variables.py
qdesignoptimizer/utils/names_parameters.py
qdesignoptimizer/utils/names_qiskit_components.py
qdesignoptimizer/utils/optimization_targets.py
qdesignoptimizer/utils/plotting.py
qdesignoptimizer/utils/utils.py
qdesignoptimizer-0.0.1.dist-info/LICENSE.txt
qdesignoptimizer-0.0.1.dist-info/METADATA
qdesignoptimizer-0.0.1.dist-info/WHEEL
qdesignoptimizer-0.0.1.dist-info/RECORD
