Metadata-Version: 2.3
Name: qdesignoptimizer
Version: 0.0.1
Summary: Optimizer for superconducting quantum chip designs
License: Apache-2.0
Keywords: Quantum
Author: 202Q-lab
Requires-Python: >=3.10,<3.11
Classifier: Programming Language :: Python :: 3
Requires-Dist: addict (==2.4.0)
Requires-Dist: cython (<3.0.0)
Requires-Dist: descartes (==1.1.0)
Requires-Dist: gdspy (==1.6.12)
Requires-Dist: geopandas (==0.12.2)
Requires-Dist: gmsh (==4.11.1)
Requires-Dist: ipykernel
Requires-Dist: ipython (==8.10.0)
Requires-Dist: matplotlib (==3.7.0)
Requires-Dist: numpy (==1.24.1)
Requires-Dist: pandas (==1.5.3)
Requires-Dist: pint (==0.20.1)
Requires-Dist: pyEPR-quantum (==0.9.*)
Requires-Dist: pyaedt (==0.6.94)
Requires-Dist: pygments (==2.14.0)
Requires-Dist: pyside2 (==5.15.2.1)
Requires-Dist: pyyaml (==6.0)
Requires-Dist: qdarkstyle (==3.1)
Requires-Dist: qutip (==4.7.1)
Requires-Dist: scipy (==1.10.0)
Requires-Dist: scqubits (==3.1.0)
Requires-Dist: shapely (==2.0.1)
